{"state-name": "", "newspaper": [{"facebook": "http://facebook.com/ShropshireStar", "city-county-lat": 52.9036, "media-subclass": "city-county", "website": "http://www.marketdraytonadvertiser.com/", "city-county-name": "Market Drayton", "name": "Market Drayton Advertiser", "rss": ["http://www.shropshirestar.com/market-drayton-advertiser/feed/"], "city-county-long": -2.4835, "video": "", "media-class": "newspaper", "twitter": "http://twitter.com/ShropshireStar", "open-search": []}], "radio": [], "tv": []}