{"state-name": "", "newspaper": [{"facebook": "https://www.facebook.com/theliverpoolecho", "city-county-lat": 53.4084, "media-subclass": "city-county", "website": "http://icliverpool.icnetwork.co.uk/", "city-county-name": "Liverpool", "name": "Liverpool Echo", "rss": ["http://icliverpool.icnetwork.co.uk/rss.xml"], "city-county-long": -2.9916, "video": "", "media-class": "newspaper", "twitter": "https://twitter.com/LivEchonews", "open-search": []}, {"facebook": "https://www.facebook.com/TheSphinxLiverpool/", "city-county-lat": 53.4084, "media-subclass": "city-county", "website": "http://liverpoolstudentmedia.com/", "city-county-name": "Liverpool", "name": "Liverpool Student Media", "rss": ["https://www.thesphinx.co.uk/comments/feed/", "https://www.thesphinx.co.uk/feed/"], "city-county-long": -2.9916, "video": "", "media-class": "newspaper", "twitter": "https://twitter.com/sphinxliverpool", "open-search": []}, {"facebook": "", "city-county-lat": 53.4084, "media-subclass": "city-county", "website": "http://www.looprevilpress.co.uk/", "city-county-name": "Liverpool", "name": "LJMU Looprevil Press", "rss": [], "city-county-long": -2.9916, "video": "", "media-class": "newspaper", "twitter": "", "open-search": []}], "radio": [], "tv": []}