{"state-name": "", "newspaper": [{"facebook": "http://www.facebook.com/shildontowncrier", "city-county-lat": 54.6334, "media-subclass": "city-county", "website": "http://www.shildontowncrier.com", "city-county-name": "Shildon", "name": "Shildon Town Crier", "rss": ["http://www.shildontowncrier.com/feed/atom/", "http://www.shildontowncrier.com/feed/"], "city-county-long": -1.6549, "video": "", "media-class": "newspaper", "twitter": "https://twitter.com/ShildonCrier", "open-search": []}], "radio": [], "tv": []}