{"state-name": "", "newspaper": [{"facebook": "https://www.facebook.com/JornaldaMarinha?fref=ts", "city-county-lat": 39.7504, "media-subclass": "city-county", "website": "http://www.jornaldamarinha.pt/", "city-county-name": "Marinha Grande", "name": "Jornal da Marinha", "rss": ["http://www.jornaldamarinha.pt/index.php?format=feed&type=atom", "http://www.jornaldamarinha.pt/index.php?format=feed&type=rss"], "city-county-long": -8.9318, "video": "", "media-class": "newspaper", "twitter": "", "open-search": []}], "radio": [], "tv": []}