{"state-name": "", "newspaper": [{"facebook": "https://www.facebook.com/pages/FlashPoint-Newspaper/111094425615906", "city-county-lat": 4.8156, "media-subclass": "city-county", "website": "http://flashpointnews.wordpress.com/", "city-county-name": "Port Harcourt", "name": "Flashpoint News", "rss": ["https://flashpointnews.wordpress.com/feed/", "https://flashpointnews.wordpress.com/comments/feed/"], "city-county-long": 7.0498, "video": "", "media-class": "newspaper", "twitter": "", "open-search": ["https://s1.wp.com/opensearch.xml", "https://flashpointnews.wordpress.com/osd.xml"]}, {"facebook": "", "city-county-lat": 4.8156, "media-subclass": "city-county", "website": "http://www.nationalnetworkonline.com/", "city-county-name": "Port Harcourt", "name": "National Network", "rss": [], "city-county-long": 7.0498, "video": "", "media-class": "newspaper", "twitter": "", "open-search": []}, {"facebook": "https://www.facebook.com/Portharcourt.telegraph/?hc_ref=PAGES_TIMELINE&fref=nf", "city-county-lat": 4.8156, "media-subclass": "city-county", "website": "https://www.facebook.com/Portharcourt.telegraph", "city-county-name": "Port Harcourt", "name": "Port Harcourt Telegraph", "rss": [], "city-county-long": 7.0498, "video": "", "media-class": "newspaper", "twitter": "", "open-search": []}, {"facebook": "", "city-county-lat": 4.8156, "media-subclass": "city-county", "website": "http://www.thenewswriterng.com/", "city-county-name": "Port Harcourt", "name": "The Newswriter", "rss": ["http://www.thenewswriterng.com/?feed=comments-rss2", "http://www.thenewswriterng.com/?feed=rss2"], "city-county-long": 7.0498, "video": "", "media-class": "newspaper", "twitter": "", "open-search": []}, {"facebook": "", "city-county-lat": 4.8156, "media-subclass": "city-county", "website": "http://www.thetidenewsonline.com/", "city-county-name": "Port Harcourt", "name": "The Tide", "rss": ["http://www.thetidenewsonline.com/feed/", "http://www.thetidenewsonline.com/comments/feed/", "http://www.thetidenewsonline.com/home/feed/"], "city-county-long": 7.0498, "video": "http://www.youtube.com/tagDiv", "media-class": "newspaper", "twitter": "https://twitter.com/TheTideNewspape", "open-search": []}], "radio": [], "tv": []}