{"state-name": "", "newspaper": [{"facebook": "https://www.facebook.com/elcarabobeno", "city-county-lat": 10.1579, "media-subclass": "city-county", "website": "http://www.el-carabobeno.com", "city-county-name": "Valencia", "name": "El Carabobeno", "rss": ["https://www.el-carabobeno.com/comments/feed/", "https://www.el-carabobeno.com/feed/", "https://www.el-carabobeno.com/news-3/feed/"], "city-county-long": -67.9972, "video": "https://www.youtube.com/user/diarioelcarabobeno", "media-class": "newspaper", "twitter": "https://twitter.com/el_carabobeno", "open-search": []}, {"facebook": "http://facebook.com/notitarde", "city-county-lat": 10.1579, "media-subclass": "city-county", "website": "http://www.notitarde.com/", "city-county-name": "Valencia", "name": "Notitarde", "rss": [], "city-county-long": -67.9972, "video": "https://www.youtube.com/user/notitardeweb", "media-class": "newspaper", "twitter": "http://twitter.com/webnotitarde", "open-search": []}], "radio": [], "tv": []}