{"state-name": "", "newspaper": [{"facebook": "https://www.facebook.com/camerountribune/", "city-county-lat": 3.848, "media-subclass": "city-county", "website": "http://www.cameroon-tribune.cm/", "city-county-name": "Yaounde", "name": "Cameroon Tribune", "rss": [], "city-county-long": 11.5021, "video": "", "media-class": "newspaper", "twitter": "https://www.twitter.com/camerountribune", "open-search": []}, {"facebook": "", "city-county-lat": 3.848, "media-subclass": "city-county", "website": "http://www.camfoot.com/", "city-county-name": "Yaounde", "name": "Camfoot", "rss": ["http://www.camfoot.com/spip.php?page=backend"], "city-county-long": 11.5021, "video": "", "media-class": "newspaper", "twitter": "", "open-search": []}], "radio": [], "tv": []}