{"state-name": "", "newspaper": [{"facebook": "https://www.facebook.com/bladetnordlys", "city-county-lat": 69.6492, "media-subclass": "city-county", "website": "http://www.nordlys.no/", "city-county-name": "Tromso", "name": "Nordlys", "rss": [], "city-county-long": 18.9553, "video": "", "media-class": "newspaper", "twitter": "https://twitter.com/bladetnordlys", "open-search": []}, {"facebook": "", "city-county-lat": 69.6492, "media-subclass": "city-county", "website": "http://www.ruijan-kaiku.no/", "city-county-name": "Tromso", "name": "Ruijan Kaiku", "rss": ["http://ruijan-kaiku.no/comments/feed/", "http://ruijan-kaiku.no/feed/"], "city-county-long": 18.9553, "video": "", "media-class": "newspaper", "twitter": "", "open-search": []}, {"facebook": "https://www.facebook.com/itromso", "city-county-lat": 69.6492, "media-subclass": "city-county", "website": "http://www.itromso.no/", "city-county-name": "Tromso", "name": "Tromso", "rss": [], "city-county-long": 18.9553, "video": "", "media-class": "newspaper", "twitter": "https://twitter.com/iTromso", "open-search": []}, {"facebook": "", "city-county-lat": 69.6492, "media-subclass": "city-county", "website": "http://tromsoby.no/", "city-county-name": "Tromso", "name": "Tromsoby", "rss": [], "city-county-long": 18.9553, "video": "", "media-class": "newspaper", "twitter": "", "open-search": []}], "radio": [], "tv": []}