{"state-name": "", "newspaper": [{"facebook": "https://www.facebook.com/banbridge.dromore.leader", "city-county-lat": 54.3487, "media-subclass": "city-county", "website": "http://www.banbridgeleader.co.uk/", "city-county-name": "Banbridge", "name": "Banbridge Leader", "rss": ["http://www.banbridgeleader.co.uk/rss/cmlink/1.7669786", "http://www.banbridgeleader.co.uk/rss/cmlink/1.7669729", "http://www.banbridgeleader.co.uk/rss/cmlink/1.7669768", "http://www.banbridgeleader.co.uk/rss/cmlink/1.7669726"], "city-county-long": -6.2705, "video": "", "media-class": "newspaper", "twitter": "https://twitter.com/banleader", "open-search": []}], "radio": [], "tv": []}