{"state-name": "", "newspaper": [{"facebook": "https://www.facebook.com/SimcoeNews", "city-county-lat": 44.3894, "media-subclass": "city-county", "website": "http://www.simcoe.com/", "city-county-name": "Barrie", "name": "Barrie Advance", "rss": [], "city-county-long": -79.6903, "video": "", "media-class": "newspaper", "twitter": "https://twitter.com/SimcoeNews", "open-search": []}, {"facebook": "https://www.facebook.com/pages/Barrie-Examiner/335403395723", "city-county-lat": 44.3894, "media-subclass": "city-county", "website": "http://www.thebarrieexaminer.com/", "city-county-name": "Barrie", "name": "Barrie Examiner", "rss": [], "city-county-long": -79.6903, "video": "", "media-class": "newspaper", "twitter": "http://www.twitter.com/BarrieExaminer", "open-search": []}], "radio": [], "tv": []}