{"state-name": "", "newspaper": [{"facebook": "", "city-county-lat": 62.3414, "media-subclass": "city-county", "website": "http://www.heroynytt.no/", "city-county-name": "Forsnevaag", "name": "Heroynytt", "rss": ["http://www.heroynytt.no/?widgetName=polarisFeeds&widgetId=9848889&getXmlFeed=true", "http://www.heroynytt.no/?widgetName=polarisFeeds&widgetId=9848891&getXmlFeed=true"], "city-county-long": 5.6311, "video": "", "media-class": "newspaper", "twitter": "", "open-search": []}], "radio": [], "tv": []}