{"state-name": "", "newspaper": [{"facebook": "http://www.facebook.com/sharer.php?p%5Bsummary%5D=%3Cp%3EH%C3%A4r+kan+du+sj%C3%A4lv+g%C3%B6ra+de+flesta+%C3%A4renden+som+r%C3%B6r+din+prenumeration.+Om+du+inte+hittar+det+du+letar+efter+%C3%A4r+du+alltid+v%C3%A4lkommen+att+kontakta+v%C3%A5rt+kundcenter.%3C%2Fp%3E&p%5Btitle%5D=Kontakta%2520oss%2520p%25C3%25A5%2520SA%2520%25E2%2580%2593%25C2%25A0h%25C3%25A4r%2520%25C3%25A4r%2520alla%2520uppgifter&p%5Burl%5D=http%3A%2F%2Fwww.salaallehanda.com%2Fallmant%2Fvalkommen-till-kundservice-1&s=100&t=Kontakta%2520oss%2520p%25C3%25A5%2520SA%2520%25E2%2580%2593%25C2%25A0h%25C3%25A4r%2520%25C3%25A4r%2520alla%2520uppgifter&u=http%3A%2F%2Fwww.salaallehanda.com%2Fallmant%2Fvalkommen-till-kundservice-1", "city-county-lat": 59.9209, "media-subclass": "city-county", "website": "http://salaallehanda.com/", "city-county-name": "Sala", "name": "Sala Allehanda", "rss": ["http://salaallehanda.com/feed", "http://salaallehanda.com/ettan.xml"], "city-county-long": 16.6063, "video": "", "media-class": "newspaper", "twitter": "", "open-search": []}], "radio": [], "tv": []}