{"state-name": "", "newspaper": [{"facebook": "http://www.facebook.com/pages/Fosna-Folket/188265581189944", "city-county-lat": 60.5438, "media-subclass": "city-county", "website": "http://www.fosna-folket.no/", "city-county-name": "Brakstad", "name": "Fosna Folket", "rss": ["http://www.fosna-folket.no/?widgetName=polarisFeeds&widgetId=7278521&getXmlFeed=true"], "city-county-long": 5.1221, "video": "", "media-class": "newspaper", "twitter": "https://twitter.com/fosnafolket", "open-search": []}], "radio": [], "tv": []}