{"state-name": "", "newspaper": [{"facebook": "https://www.facebook.com/LeylandGuardian", "city-county-lat": 53.6979, "media-subclass": "city-county", "website": "http://www.leylandguardian.co.uk/", "city-county-name": "Leyland", "name": "Leyland Guardian", "rss": ["http://www.leylandguardian.co.uk/rss/cmlink/1.8201479", "http://www.leylandguardian.co.uk/rss/cmlink/1.8201434", "http://www.leylandguardian.co.uk/rss/cmlink/1.8201494", "http://www.leylandguardian.co.uk/rss/cmlink/1.8201437"], "city-county-long": -2.6955, "video": "", "media-class": "newspaper", "twitter": "https://twitter.com/guardianleyland", "open-search": []}], "radio": [], "tv": []}