{"state-name": "", "newspaper": [{"facebook": "http://www.facebook.com/dnnonline", "city-county-lat": 51.0504, "media-subclass": "city-county", "website": "http://www.dnn-online.de/", "city-county-name": "Dresden", "name": "Dresdner Neueste Nachrichten", "rss": [], "city-county-long": 13.7373, "video": "", "media-class": "newspaper", "twitter": "http://twitter.com/dnn_online", "open-search": []}, {"facebook": "http://www.facebook.com/szonline?v=wall", "city-county-lat": 51.0504, "media-subclass": "city-county", "website": "http://www.sz-online.de/", "city-county-name": "Dresden", "name": "Sächsische Zeitung", "rss": ["http://www.sz-online.de/News/Dippoldiswalde.rss", "http://www.sz-online.de/News/Goerlitz.rss", "http://www.sz-online.de/News/Kamenz-Sport.rss", "http://www.sz-online.de/News/Niesky.rss", "http://www.sz-online.de/News/Dresdner-Land-Sport.rss", "http://www.sz-online.de/News/Kultur.rss", "http://www.sz-online.de/News/Grossenhain-Sport.rss", "http://www.sz-online.de/News/Weisswasser-Sport.rss", "http://www.sz-online.de/News/Pirna.rss", "http://www.sz-online.de/News/Bischofswerda-Sport.rss", "http://www.sz-online.de/News/Riesa-Sport.rss", "http://www.sz-online.de/News/Goerlitz-Sport.rss", "http://www.sz-online.de/News/Meissen.rss", "http://www.sz-online.de/News/Sebnitz.rss", "http://www.sz-online.de/News/Hoyerswerda.rss", "http://www.sz-online.de/News/Dresdner-Land.rss", "http://www.sz-online.de/News/Panorama.rss", "http://www.sz-online.de/News/Loebau.rss", "http://www.sz-online.de/News/Roedertal.rss", "http://www.sz-online.de/News/Bautzen-Sport.rss", "http://www.sz-online.de/News/Doebeln-Sport.rss", "http://www.sz-online.de/News/Freital.rss", "http://www.sz-online.de/News/Weisswasser.rss", "http://www.sz-online.de/News/Doebeln.rss", "http://www.sz-online.de/News/Sport.rss", "http://www.sz-online.de/News/Sebnitz-Sport.rss", "http://www.sz-online.de/News/Zittau.rss", "http://www.sz-online.de/News/Hoyerswerda-Sport.rss", "http://www.sz-online.de/News/Dresden-Sport.rss", "http://www.sz-online.de/News/Dynamo-Dresden.rss", "http://www.sz-online.de/News/Riesa.rss", "http://www.sz-online.de/News/Zittau-Sport.rss", "http://www.sz-online.de/News/Politik.rss", "http://www.sz-online.de/News/Roedertal-Sport.rss", "http://www.sz-online.de/News/Multimedia.rss", "http://www.sz-online.de/News/Bischofswerda.rss", "http://www.sz-online.de/News/Wirtschaft.rss", "http://www.sz-online.de/News/Meissen-Sport.rss", "http://www.sz-online.de/News/Pirna-Sport.rss", "http://www.sz-online.de/News/Loebau-Sport.rss", "http://www.sz-online.de/News/Wissen.rss", "http://www.sz-online.de/News/Kamenz.rss", "http://www.sz-online.de/News/Niesky-Sport.rss", "http://www.sz-online.de/News/Freital-Sport.rss", "http://www.sz-online.de/News/Dresden.rss", "http://www.sz-online.de/News/Bautzen.rss", "http://www.sz-online.de/News/Grossenhain.rss", "http://www.sz-online.de/News/Sachsen.rss", "http://www.sz-online.de/News/Dippoldiswalde-Sport.rss"], "city-county-long": 13.7373, "video": "", "media-class": "newspaper", "twitter": "http://twitter.com/szonline", "open-search": []}], "radio": [], "tv": []}