{"state-name": "", "newspaper": [{"facebook": "http://www.facebook.com/pages/Weston-Worle-Somerset-Mercury/171907359493669", "city-county-lat": 51.3474, "media-subclass": "city-county", "website": "http://www.thewestonmercury.co.uk/news", "city-county-name": "Weston-Super-Mare", "name": "Weston Mercury", "rss": ["http://www.thewestonmercury.co.uk/newscmlink/rss-feed-1-3920027"], "city-county-long": -2.9773, "video": "", "media-class": "newspaper", "twitter": "https://twitter.com/WSMERCURY", "open-search": []}], "radio": [], "tv": []}