{"state-name": "", "newspaper": [{"facebook": "http://www.facebook.com/pages/Chilliwack-Progress/145738394744", "city-county-lat": 49.1579, "media-subclass": "city-county", "website": "http://www.theprogress.com/", "city-county-name": "Chilliwack", "name": "Chilliwack Progress", "rss": ["http://www.theprogress.com/opinion/index.rss", "http://www.theprogress.com/opinion/letters/index.rss", "http://www.theprogress.com/community/index.rss", "http://www.theprogress.com/news/index.rss", "http://www.theprogress.com/sports/index.rss", "http://www.theprogress.com/entertainment/index.rss", "http://www.theprogress.com/lifestyles/index.rss", "http://www.theprogress.com/business/index.rss"], "city-county-long": -121.9515, "video": "", "media-class": "newspaper", "twitter": "http://twitter.com/#!/theprogress", "open-search": []}], "radio": [], "tv": []}