{"state-name": "", "newspaper": [{"facebook": "http://www.facebook.com/pages/Divyabhaskar/252027794243", "city-county-lat": 23.0225, "media-subclass": "city-county", "website": "http://www.divyabhaskar.co.in/", "city-county-name": "Ahmadabad", "name": "Divya Bhaskar", "rss": [], "city-county-long": 72.5714, "video": "http://www.youtube.com/user/dbnewsweb", "media-class": "newspaper", "twitter": "http://twitter.com/Divya_Bhaskar", "open-search": []}, {"facebook": "http://www.facebook.com/gujarat.samachar.news", "city-county-lat": 23.0225, "media-subclass": "city-county", "website": "http://www.gujaratsamachar.com/", "city-county-name": "Ahmadabad", "name": "Gujarat Samachar", "rss": [], "city-county-long": 72.5714, "video": "https://www.youtube.com/GujaratSamacharVideo", "media-class": "newspaper", "twitter": "http://twitter.com/gujratsamachar", "open-search": []}, {"facebook": "", "city-county-lat": 23.0225, "media-subclass": "city-county", "website": "http://www.nirmalmetro.in/", "city-county-name": "Ahmadabad", "name": "Nirmal Metro", "rss": [], "city-county-long": 72.5714, "video": "https://www.youtube.com/channel/UCRHl0PWnddC4YOxjRTOBooA", "media-class": "newspaper", "twitter": "", "open-search": []}, {"facebook": "https://www.facebook.com/SambhaavNews?ref=hl", "city-county-lat": 23.0225, "media-subclass": "city-county", "website": "http://www.sambhaav.com", "city-county-name": "Ahmadabad", "name": "Sambhaav", "rss": ["http://sambhaavnews.com/feed/", "http://sambhaavnews.com/home/feed/"], "city-county-long": 72.5714, "video": "", "media-class": "newspaper", "twitter": "https://twitter.com/SambhaavNews", "open-search": []}, {"facebook": "https://www.facebook.com/sandeshnewspaper", "city-county-lat": 23.0225, "media-subclass": "city-county", "website": "http://www.sandesh.com/", "city-county-name": "Ahmadabad", "name": "Sandesh", "rss": ["http://sandesh.com/comments/feed/", "http://sandesh.com/feed/"], "city-county-long": 72.5714, "video": "https://www.youtube.com/watch?v=0fSJTdzxDv8", "media-class": "newspaper", "twitter": "http://www.twitter.com/sandeshnews", "open-search": []}], "radio": [], "tv": []}